ppp/__init__.py
ppp/data/ppp-gdp.csv
pppfy/__init__.py
pppfy/converter.py
pppfy-2024.5.3.dist-info/LICENSE
pppfy-2024.5.3.dist-info/METADATA
pppfy-2024.5.3.dist-info/WHEEL
pppfy-2024.5.3.dist-info/top_level.txt
pppfy-2024.5.3.dist-info/RECORD
