Metadata-Version: 2.1
Name: pppfy
Version: 2024.5.3
Summary: A Python package to get prices based on Purchasing Power Parity (PPP)
Home-page: https://github.com/musicmuni/pppfy
Author: Gopala Krishna Koduri
Author-email: gopal@riyazapp.com
Project-URL: Source Code, https://github.com/musicmuni/pppfy
Project-URL: Issue Tracker, https://github.com/musicmuni/pppfy/issues
Project-URL: Connect w/ Author, https://linkedin.com/in/gopalkoduri
Project-URL: Riyaz - Learn to sing, https://riyazapp.com
Classifier: Development Status :: 3 - Alpha
Classifier: Intended Audience :: Developers
Classifier: Topic :: Software Development :: Build Tools
Classifier: License :: OSI Approved :: MIT License
Classifier: Programming Language :: Python :: 3
Classifier: Programming Language :: Python :: 3.7
Classifier: Programming Language :: Python :: 3.8
Classifier: Programming Language :: Python :: 3.9
Classifier: Programming Language :: Python :: 3.10
Classifier: Programming Language :: Python :: 3.11
License-File: LICENSE
